chat_template_detector/__init__.py
chat_template_detector/cli.py
chat_template_detector/detector.py
chat_template_detector/templates.py
chat_template_detector-0.1.0.dist-info/licenses/LICENSE
chat_template_detector-0.1.0.dist-info/METADATA
chat_template_detector-0.1.0.dist-info/WHEEL
chat_template_detector-0.1.0.dist-info/entry_points.txt
chat_template_detector-0.1.0.dist-info/top_level.txt
chat_template_detector-0.1.0.dist-info/RECORD
