Metadata-Version: 2.4
Name: chat-template-detector
Version: 0.1.0
Summary: Detect chat template mismatches in LLM fine-tuning
Author: ClarifyIntel
License: MIT
Project-URL: Homepage, https://github.com/clarifyintel/chat-template-detector
Project-URL: Repository, https://github.com/clarifyintel/chat-template-detector
Project-URL: Issues, https://github.com/clarifyintel/chat-template-detector/issues
Classifier: Development Status :: 3 - Alpha
Classifier: Intended Audience :: Developers
Classifier: License :: OSI Approved :: MIT License
Classifier: Programming Language :: Python :: 3
Classifier: Programming Language :: Python :: 3.8
Classifier: Programming Language :: Python :: 3.9
Classifier: Programming Language :: Python :: 3.10
Classifier: Programming Language :: Python :: 3.11
Requires-Python: >=3.8
License-File: LICENSE
Requires-Dist: click>=8.0
Requires-Dist: jinja2>=3.0
Requires-Dist: pyyaml>=6.0
Provides-Extra: dev
Requires-Dist: pytest>=7.0; extra == "dev"
Requires-Dist: black>=22.0; extra == "dev"
Requires-Dist: flake8>=5.0; extra == "dev"
Dynamic: license-file
